dissect/cstruct/__init__.py
dissect/cstruct/bitbuffer.py
dissect/cstruct/compiler.py
dissect/cstruct/cstruct.py
dissect/cstruct/exceptions.py
dissect/cstruct/expression.py
dissect/cstruct/parser.py
dissect/cstruct/utils.py
dissect/cstruct/tools/__init__.py
dissect/cstruct/tools/stubgen.py
dissect/cstruct/types/__init__.py
dissect/cstruct/types/base.py
dissect/cstruct/types/char.py
dissect/cstruct/types/enum.py
dissect/cstruct/types/flag.py
dissect/cstruct/types/int.py
dissect/cstruct/types/leb128.py
dissect/cstruct/types/packed.py
dissect/cstruct/types/pointer.py
dissect/cstruct/types/structure.py
dissect/cstruct/types/void.py
dissect/cstruct/types/wchar.py
dissect_cstruct-4.6.dist-info/licenses/COPYRIGHT
dissect_cstruct-4.6.dist-info/licenses/LICENSE
dissect_cstruct-4.6.dist-info/METADATA
dissect_cstruct-4.6.dist-info/WHEEL
dissect_cstruct-4.6.dist-info/entry_points.txt
dissect_cstruct-4.6.dist-info/top_level.txt
dissect_cstruct-4.6.dist-info/RECORD
