Metadata-Version: 2.4
Name: dissect.cstruct
Version: 4.6
Summary: A Dissect module implementing a parser for C-like structures: structure parsing in Python made easy
Author-email: Dissect Team <dissect@fox-it.com>
License: Apache License 2.0
Project-URL: homepage, https://dissect.tools
Project-URL: documentation, https://docs.dissect.tools/en/latest/projects/dissect.cstruct
Project-URL: repository, https://github.com/fox-it/dissect.cstruct
Project-URL: changelog, https://github.com/fox-it/dissect.cstruct/blob/main/CHANGELOG.md
Classifier: Development Status :: 5 - Production/Stable
Classifier: Environment :: Console
Classifier: Intended Audience :: Developers
Classifier: Intended Audience :: Information Technology
Classifier: License :: OSI Approved
Classifier: Operating System :: OS Independent
Classifier: Programming Language :: Python :: 3
Classifier: Topic :: Internet :: Log Analysis
Classifier: Topic :: Scientific/Engineering :: Information Analysis
Classifier: Topic :: Security
Classifier: Topic :: Utilities
Requires-Python: ~=3.9
License-File: LICENSE
License-File: COPYRIGHT
Provides-Extra: dev
Requires-Dist: typing_extensions; extra == "dev"
Dynamic: license-file
